{
    "key": "group_5c6f22d638b25",
    "title": "Resource Library Single",
    "fields": [
        {
            "key": "field_5c6f2340b98a3",
            "label": "Resource Content",
            "name": "resource_content",
            "type": "flexible_content",
            "instructions": "",
            "required": 0,
            "conditional_logic": 0,
            "wrapper": {
                "width": "",
                "class": "",
                "id": ""
            },
            "layouts": {
                "5c36f1630ea64": {
                    "key": "5c36f1630ea64",
                    "name": "text_block",
                    "label": "Text Block",
                    "display": "block",
                    "sub_fields": [
                        {
                            "key": "field_5c6f2341b98a4",
                            "label": "WYSIWYG",
                            "name": "wysiwyg",
                            "type": "wysiwyg",
                            "instructions": "",
                            "required": 0,
                            "conditional_logic": 0,
                            "wrapper": {
                                "width": "",
                                "class": "",
                                "id": ""
                            },
                            "default_value": "",
                            "tabs": "all",
                            "toolbar": "full",
                            "media_upload": 0,
                            "delay": 0
                        }
                    ],
                    "min": "",
                    "max": ""
                },
                "layout_5c36f40567ae9": {
                    "key": "layout_5c36f40567ae9",
                    "name": "video_block",
                    "label": "Video Block",
                    "display": "block",
                    "sub_fields": [
                        {
                            "key": "field_5c6f2341b98a5",
                            "label": "Video",
                            "name": "video",
                            "type": "post_object",
                            "instructions": "",
                            "required": 0,
                            "conditional_logic": 0,
                            "wrapper": {
                                "width": "",
                                "class": "",
                                "id": ""
                            },
                            "post_type": [
                                "videos"
                            ],
                            "taxonomy": "",
                            "allow_null": 0,
                            "multiple": 0,
                            "return_format": "object",
                            "ui": 1
                        }
                    ],
                    "min": "",
                    "max": ""
                },
                "layout_5c36f9901d400": {
                    "key": "layout_5c36f9901d400",
                    "name": "banner_block",
                    "label": "Banner Block",
                    "display": "block",
                    "sub_fields": [
                        {
                            "key": "field_5c6f2341b98a7",
                            "label": "Summary",
                            "name": "summary",
                            "type": "group",
                            "instructions": "",
                            "required": 0,
                            "conditional_logic": [
                                [
                                    {
                                        "field": "field_5c6f2341b98a6",
                                        "operator": "==",
                                        "value": "Summary"
                                    }
                                ]
                            ],
                            "wrapper": {
                                "width": "",
                                "class": "",
                                "id": ""
                            },
                            "layout": "row",
                            "sub_fields": [
                                {
                                    "key": "field_5c6f2341b98a8",
                                    "label": "Headline",
                                    "name": "headline",
                                    "type": "text",
                                    "instructions": "",
                                    "required": 0,
                                    "conditional_logic": 0,
                                    "wrapper": {
                                        "width": "",
                                        "class": "",
                                        "id": ""
                                    },
                                    "default_value": "",
                                    "placeholder": "",
                                    "prepend": "",
                                    "append": "",
                                    "maxlength": ""
                                },
                                {
                                    "key": "field_5c6f2341b98a9",
                                    "label": "Text",
                                    "name": "text",
                                    "type": "wysiwyg",
                                    "instructions": "",
                                    "required": 0,
                                    "conditional_logic": 0,
                                    "wrapper": {
                                        "width": "",
                                        "class": "",
                                        "id": ""
                                    },
                                    "default_value": "",
                                    "tabs": "all",
                                    "toolbar": "very_simple",
                                    "media_upload": 0,
                                    "delay": 0
                                },
                                {
                                    "key": "field_5c6f2341b98aa",
                                    "label": "Link",
                                    "name": "link",
                                    "type": "link",
                                    "instructions": "",
                                    "required": 0,
                                    "conditional_logic": 0,
                                    "wrapper": {
                                        "width": "",
                                        "class": "",
                                        "id": ""
                                    },
                                    "return_format": "array"
                                }
                            ]
                        },
                        {
                            "key": "field_5c6f2341b98a6",
                            "label": "Type",
                            "name": "type",
                            "type": "select",
                            "instructions": "",
                            "required": 0,
                            "conditional_logic": 0,
                            "wrapper": {
                                "width": "",
                                "class": "",
                                "id": ""
                            },
                            "choices": {
                                "Summary": "Summary",
                                "Quote": "Quote"
                            },
                            "default_value": [
                                "Summary"
                            ],
                            "allow_null": 0,
                            "multiple": 0,
                            "ui": 0,
                            "ajax": 0,
                            "return_format": "value",
                            "placeholder": ""
                        },
                        {
                            "key": "field_5c6f2341b98ab",
                            "label": "Quote",
                            "name": "quote",
                            "type": "group",
                            "instructions": "",
                            "required": 0,
                            "conditional_logic": [
                                [
                                    {
                                        "field": "field_5c6f2341b98a6",
                                        "operator": "==",
                                        "value": "Quote"
                                    }
                                ]
                            ],
                            "wrapper": {
                                "width": "",
                                "class": "",
                                "id": ""
                            },
                            "layout": "row",
                            "sub_fields": [
                                {
                                    "key": "field_5c6f2341b98ac",
                                    "label": "Text",
                                    "name": "text",
                                    "type": "wysiwyg",
                                    "instructions": "",
                                    "required": 0,
                                    "conditional_logic": 0,
                                    "wrapper": {
                                        "width": "",
                                        "class": "",
                                        "id": ""
                                    },
                                    "default_value": "",
                                    "tabs": "all",
                                    "toolbar": "very_simple",
                                    "media_upload": 0,
                                    "delay": 0
                                },
                                {
                                    "key": "field_5c6f2341b98ad",
                                    "label": "Credit Name",
                                    "name": "credit_name",
                                    "type": "text",
                                    "instructions": "",
                                    "required": 0,
                                    "conditional_logic": 0,
                                    "wrapper": {
                                        "width": "",
                                        "class": "",
                                        "id": ""
                                    },
                                    "default_value": "",
                                    "placeholder": "",
                                    "prepend": "",
                                    "append": "",
                                    "maxlength": ""
                                },
                                {
                                    "key": "field_5c6f2341b98ae",
                                    "label": "Credit Title",
                                    "name": "credit_title",
                                    "type": "text",
                                    "instructions": "",
                                    "required": 0,
                                    "conditional_logic": 0,
                                    "wrapper": {
                                        "width": "",
                                        "class": "",
                                        "id": ""
                                    },
                                    "default_value": "",
                                    "placeholder": "",
                                    "prepend": "",
                                    "append": "",
                                    "maxlength": ""
                                }
                            ]
                        },
                        {
                            "key": "field_5c6f2341b98af",
                            "label": "Image",
                            "name": "image",
                            "type": "image",
                            "instructions": "",
                            "required": 0,
                            "conditional_logic": 0,
                            "wrapper": {
                                "width": "",
                                "class": "",
                                "id": ""
                            },
                            "return_format": "array",
                            "preview_size": "thumbnail",
                            "library": "all",
                            "min_width": "",
                            "min_height": "",
                            "min_size": "",
                            "max_width": "",
                            "max_height": "",
                            "max_size": "",
                            "mime_types": ""
                        },
                        {
                            "key": "field_5c6f2341b98b0",
                            "label": "Caption",
                            "name": "caption",
                            "type": "text",
                            "instructions": "",
                            "required": 0,
                            "conditional_logic": 0,
                            "wrapper": {
                                "width": "",
                                "class": "",
                                "id": ""
                            },
                            "default_value": "",
                            "placeholder": "",
                            "prepend": "",
                            "append": "",
                            "maxlength": ""
                        }
                    ],
                    "min": "",
                    "max": ""
                },
                "layout_5c36ff3c8ae86": {
                    "key": "layout_5c36ff3c8ae86",
                    "name": "figure_block",
                    "label": "Figure Block",
                    "display": "block",
                    "sub_fields": [
                        {
                            "key": "field_5c6f2341b98b1",
                            "label": "Figure",
                            "name": "figure",
                            "type": "clone",
                            "instructions": "",
                            "required": 0,
                            "conditional_logic": 0,
                            "wrapper": {
                                "width": "",
                                "class": "",
                                "id": ""
                            },
                            "clone": [
                                "group_5c36fde166e88"
                            ],
                            "display": "group",
                            "layout": "row",
                            "prefix_label": 0,
                            "prefix_name": 0,
                            "sub_fields": [
                                {
                                    "ID": 0,
                                    "key": "field_5c36fe2528914",
                                    "label": "Enlarge",
                                    "name": "enlarge",
                                    "prefix": "acf",
                                    "type": "true_false",
                                    "value": null,
                                    "menu_order": 0,
                                    "instructions": "",
                                    "required": 0,
                                    "id": "",
                                    "class": "",
                                    "conditional_logic": 0,
                                    "parent": "group_5c36fde166e88",
                                    "wrapper": {
                                        "width": "",
                                        "class": "",
                                        "id": ""
                                    },
                                    "message": "",
                                    "default_value": 0,
                                    "ui": 1,
                                    "ui_on_text": "Enlarge Button",
                                    "ui_off_text": "No Enlarge Button",
                                    "_name": "enlarge",
                                    "_valid": 1,
                                    "_clone": "field_5c6f2341b98b1",
                                    "parent_layout": "layout_5c36ff3c8ae86",
                                    "__key": "field_5c36fe2528914",
                                    "__name": "enlarge",
                                    "__label": "Enlarge"
                                },
                                {
                                    "ID": 0,
                                    "key": "field_5c36fdfa28913",
                                    "label": "Image",
                                    "name": "image",
                                    "prefix": "acf",
                                    "type": "image",
                                    "value": null,
                                    "menu_order": 0,
                                    "instructions": "",
                                    "required": 0,
                                    "id": "",
                                    "class": "",
                                    "conditional_logic": 0,
                                    "parent": "group_5c36fde166e88",
                                    "wrapper": {
                                        "width": "",
                                        "class": "",
                                        "id": ""
                                    },
                                    "return_format": "array",
                                    "preview_size": "thumbnail",
                                    "library": "all",
                                    "min_width": "",
                                    "min_height": "",
                                    "min_size": "",
                                    "max_width": "",
                                    "max_height": "",
                                    "max_size": "",
                                    "mime_types": "",
                                    "_name": "image",
                                    "_valid": 1,
                                    "_clone": "field_5c6f2341b98b1",
                                    "parent_layout": "layout_5c36ff3c8ae86",
                                    "__key": "field_5c36fdfa28913",
                                    "__name": "image",
                                    "__label": "Image"
                                },
                                {
                                    "ID": 0,
                                    "key": "field_5c36febc28915",
                                    "label": "Caption",
                                    "name": "caption",
                                    "prefix": "acf",
                                    "type": "text",
                                    "value": null,
                                    "menu_order": 0,
                                    "instructions": "",
                                    "required": 0,
                                    "id": "",
                                    "class": "",
                                    "conditional_logic": 0,
                                    "parent": "group_5c36fde166e88",
                                    "wrapper": {
                                        "width": "",
                                        "class": "",
                                        "id": ""
                                    },
                                    "default_value": "",
                                    "placeholder": "",
                                    "prepend": "",
                                    "append": "",
                                    "maxlength": "",
                                    "_name": "caption",
                                    "_valid": 1,
                                    "_clone": "field_5c6f2341b98b1",
                                    "parent_layout": "layout_5c36ff3c8ae86",
                                    "__key": "field_5c36febc28915",
                                    "__name": "caption",
                                    "__label": "Caption"
                                }
                            ]
                        }
                    ],
                    "min": "",
                    "max": ""
                },
                "layout_5c37020f21ff7": {
                    "key": "layout_5c37020f21ff7",
                    "name": "two_figure_block",
                    "label": "Two Figure Block",
                    "display": "block",
                    "sub_fields": [
                        {
                            "key": "field_5c6f2341b98b3",
                            "label": "Figure B",
                            "name": "figure_b",
                            "type": "clone",
                            "instructions": "",
                            "required": 0,
                            "conditional_logic": 0,
                            "wrapper": {
                                "width": "",
                                "class": "",
                                "id": ""
                            },
                            "clone": [
                                "group_5c36fde166e88"
                            ],
                            "display": "group",
                            "layout": "block",
                            "prefix_label": 0,
                            "prefix_name": 1,
                            "sub_fields": [
                                {
                                    "ID": 0,
                                    "key": "field_5c36fe2528914",
                                    "label": "Enlarge",
                                    "name": "figure_b_enlarge",
                                    "prefix": "acf",
                                    "type": "true_false",
                                    "value": null,
                                    "menu_order": 0,
                                    "instructions": "",
                                    "required": 0,
                                    "id": "",
                                    "class": "",
                                    "conditional_logic": 0,
                                    "parent": "group_5c36fde166e88",
                                    "wrapper": {
                                        "width": "",
                                        "class": "",
                                        "id": ""
                                    },
                                    "message": "",
                                    "default_value": 0,
                                    "ui": 1,
                                    "ui_on_text": "Enlarge Button",
                                    "ui_off_text": "No Enlarge Button",
                                    "_name": "enlarge",
                                    "_valid": 1,
                                    "_clone": "field_5c6f2341b98b3",
                                    "parent_layout": "layout_5c37020f21ff7",
                                    "__key": "field_5c36fe2528914",
                                    "__name": "enlarge",
                                    "__label": "Enlarge"
                                },
                                {
                                    "ID": 0,
                                    "key": "field_5c36fdfa28913",
                                    "label": "Image",
                                    "name": "figure_b_image",
                                    "prefix": "acf",
                                    "type": "image",
                                    "value": null,
                                    "menu_order": 0,
                                    "instructions": "",
                                    "required": 0,
                                    "id": "",
                                    "class": "",
                                    "conditional_logic": 0,
                                    "parent": "group_5c36fde166e88",
                                    "wrapper": {
                                        "width": "",
                                        "class": "",
                                        "id": ""
                                    },
                                    "return_format": "array",
                                    "preview_size": "thumbnail",
                                    "library": "all",
                                    "min_width": "",
                                    "min_height": "",
                                    "min_size": "",
                                    "max_width": "",
                                    "max_height": "",
                                    "max_size": "",
                                    "mime_types": "",
                                    "_name": "image",
                                    "_valid": 1,
                                    "_clone": "field_5c6f2341b98b3",
                                    "parent_layout": "layout_5c37020f21ff7",
                                    "__key": "field_5c36fdfa28913",
                                    "__name": "image",
                                    "__label": "Image"
                                },
                                {
                                    "ID": 0,
                                    "key": "field_5c36febc28915",
                                    "label": "Caption",
                                    "name": "figure_b_caption",
                                    "prefix": "acf",
                                    "type": "text",
                                    "value": null,
                                    "menu_order": 0,
                                    "instructions": "",
                                    "required": 0,
                                    "id": "",
                                    "class": "",
                                    "conditional_logic": 0,
                                    "parent": "group_5c36fde166e88",
                                    "wrapper": {
                                        "width": "",
                                        "class": "",
                                        "id": ""
                                    },
                                    "default_value": "",
                                    "placeholder": "",
                                    "prepend": "",
                                    "append": "",
                                    "maxlength": "",
                                    "_name": "caption",
                                    "_valid": 1,
                                    "_clone": "field_5c6f2341b98b3",
                                    "parent_layout": "layout_5c37020f21ff7",
                                    "__key": "field_5c36febc28915",
                                    "__name": "caption",
                                    "__label": "Caption"
                                }
                            ]
                        },
                        {
                            "key": "field_5c6f2341b98b2",
                            "label": "Figure A",
                            "name": "figure_a",
                            "type": "clone",
                            "instructions": "",
                            "required": 0,
                            "conditional_logic": 0,
                            "wrapper": {
                                "width": "",
                                "class": "",
                                "id": ""
                            },
                            "clone": [
                                "group_5c36fde166e88"
                            ],
                            "display": "group",
                            "layout": "block",
                            "prefix_label": 0,
                            "prefix_name": 1,
                            "sub_fields": [
                                {
                                    "ID": 0,
                                    "key": "field_5c36fe2528914",
                                    "label": "Enlarge",
                                    "name": "figure_a_enlarge",
                                    "prefix": "acf",
                                    "type": "true_false",
                                    "value": null,
                                    "menu_order": 0,
                                    "instructions": "",
                                    "required": 0,
                                    "id": "",
                                    "class": "",
                                    "conditional_logic": 0,
                                    "parent": "group_5c36fde166e88",
                                    "wrapper": {
                                        "width": "",
                                        "class": "",
                                        "id": ""
                                    },
                                    "message": "",
                                    "default_value": 0,
                                    "ui": 1,
                                    "ui_on_text": "Enlarge Button",
                                    "ui_off_text": "No Enlarge Button",
                                    "_name": "enlarge",
                                    "_valid": 1,
                                    "_clone": "field_5c6f2341b98b2",
                                    "parent_layout": "layout_5c37020f21ff7",
                                    "__key": "field_5c36fe2528914",
                                    "__name": "enlarge",
                                    "__label": "Enlarge"
                                },
                                {
                                    "ID": 0,
                                    "key": "field_5c36fdfa28913",
                                    "label": "Image",
                                    "name": "figure_a_image",
                                    "prefix": "acf",
                                    "type": "image",
                                    "value": null,
                                    "menu_order": 0,
                                    "instructions": "",
                                    "required": 0,
                                    "id": "",
                                    "class": "",
                                    "conditional_logic": 0,
                                    "parent": "group_5c36fde166e88",
                                    "wrapper": {
                                        "width": "",
                                        "class": "",
                                        "id": ""
                                    },
                                    "return_format": "array",
                                    "preview_size": "thumbnail",
                                    "library": "all",
                                    "min_width": "",
                                    "min_height": "",
                                    "min_size": "",
                                    "max_width": "",
                                    "max_height": "",
                                    "max_size": "",
                                    "mime_types": "",
                                    "_name": "image",
                                    "_valid": 1,
                                    "_clone": "field_5c6f2341b98b2",
                                    "parent_layout": "layout_5c37020f21ff7",
                                    "__key": "field_5c36fdfa28913",
                                    "__name": "image",
                                    "__label": "Image"
                                },
                                {
                                    "ID": 0,
                                    "key": "field_5c36febc28915",
                                    "label": "Caption",
                                    "name": "figure_a_caption",
                                    "prefix": "acf",
                                    "type": "text",
                                    "value": null,
                                    "menu_order": 0,
                                    "instructions": "",
                                    "required": 0,
                                    "id": "",
                                    "class": "",
                                    "conditional_logic": 0,
                                    "parent": "group_5c36fde166e88",
                                    "wrapper": {
                                        "width": "",
                                        "class": "",
                                        "id": ""
                                    },
                                    "default_value": "",
                                    "placeholder": "",
                                    "prepend": "",
                                    "append": "",
                                    "maxlength": "",
                                    "_name": "caption",
                                    "_valid": 1,
                                    "_clone": "field_5c6f2341b98b2",
                                    "parent_layout": "layout_5c37020f21ff7",
                                    "__key": "field_5c36febc28915",
                                    "__name": "caption",
                                    "__label": "Caption"
                                }
                            ]
                        }
                    ],
                    "min": "",
                    "max": ""
                },
                "layout_5c370ae05e8d5": {
                    "key": "layout_5c370ae05e8d5",
                    "name": "gallery_carousel_block",
                    "label": "Gallery Carousel Block",
                    "display": "block",
                    "sub_fields": [
                        {
                            "key": "field_5c6f2341b98b4",
                            "label": "images",
                            "name": "images",
                            "type": "gallery",
                            "instructions": "",
                            "required": 0,
                            "conditional_logic": 0,
                            "wrapper": {
                                "width": "",
                                "class": "",
                                "id": ""
                            },
                            "min": "",
                            "max": "",
                            "insert": "append",
                            "library": "all",
                            "min_width": "",
                            "min_height": "",
                            "min_size": "",
                            "max_width": "",
                            "max_height": "",
                            "max_size": "",
                            "mime_types": ""
                        }
                    ],
                    "min": "",
                    "max": ""
                },
                "layout_5c386282126fa": {
                    "key": "layout_5c386282126fa",
                    "name": "thumbnail_links_block",
                    "label": "Thumbnail Links Block",
                    "display": "block",
                    "sub_fields": [
                        {
                            "key": "field_5c6f2341b98b5",
                            "label": "Links",
                            "name": "links",
                            "type": "repeater",
                            "instructions": "",
                            "required": 0,
                            "conditional_logic": 0,
                            "wrapper": {
                                "width": "",
                                "class": "",
                                "id": ""
                            },
                            "collapsed": "",
                            "min": 3,
                            "max": 0,
                            "layout": "row",
                            "button_label": "",
                            "sub_fields": [
                                {
                                    "key": "field_5c6f2341b98b6",
                                    "label": "Image",
                                    "name": "image",
                                    "type": "image",
                                    "instructions": "",
                                    "required": 0,
                                    "conditional_logic": 0,
                                    "wrapper": {
                                        "width": "",
                                        "class": "",
                                        "id": ""
                                    },
                                    "return_format": "array",
                                    "preview_size": "thumbnail",
                                    "library": "all",
                                    "min_width": "",
                                    "min_height": "",
                                    "min_size": "",
                                    "max_width": "",
                                    "max_height": "",
                                    "max_size": "",
                                    "mime_types": ""
                                },
                                {
                                    "key": "field_5c6f2341b98b7",
                                    "label": "Link",
                                    "name": "link",
                                    "type": "link",
                                    "instructions": "",
                                    "required": 0,
                                    "conditional_logic": 0,
                                    "wrapper": {
                                        "width": "",
                                        "class": "",
                                        "id": ""
                                    },
                                    "return_format": "array"
                                }
                            ]
                        }
                    ],
                    "min": "",
                    "max": ""
                },
                "layout_5c3866f29aef3": {
                    "key": "layout_5c3866f29aef3",
                    "name": "gallery_thumbnail_block",
                    "label": "Gallery Thumbnail Block",
                    "display": "block",
                    "sub_fields": [
                        {
                            "key": "field_5c6f2341b98b8",
                            "label": "images",
                            "name": "images",
                            "type": "gallery",
                            "instructions": "",
                            "required": 0,
                            "conditional_logic": 0,
                            "wrapper": {
                                "width": "",
                                "class": "",
                                "id": ""
                            },
                            "min": "",
                            "max": "",
                            "insert": "append",
                            "library": "all",
                            "min_width": "",
                            "min_height": "",
                            "min_size": "",
                            "max_width": "",
                            "max_height": "",
                            "max_size": "",
                            "mime_types": ""
                        }
                    ],
                    "min": "",
                    "max": ""
                },
                "layout_5c386aadd0a31": {
                    "key": "layout_5c386aadd0a31",
                    "name": "color_callout_block",
                    "label": "Color Callout Block",
                    "display": "block",
                    "sub_fields": [
                        {
                            "key": "field_5c6f2341b98b9",
                            "label": "callouts",
                            "name": "callouts",
                            "type": "repeater",
                            "instructions": "",
                            "required": 0,
                            "conditional_logic": 0,
                            "wrapper": {
                                "width": "",
                                "class": "",
                                "id": ""
                            },
                            "collapsed": "field_5c386af0d0a33",
                            "min": 1,
                            "max": 0,
                            "layout": "row",
                            "button_label": "",
                            "sub_fields": [
                                {
                                    "key": "field_5c6f2341b98ba",
                                    "label": "Background Color",
                                    "name": "background_color",
                                    "type": "select",
                                    "instructions": "",
                                    "required": 0,
                                    "conditional_logic": 0,
                                    "wrapper": {
                                        "width": "",
                                        "class": "",
                                        "id": ""
                                    },
                                    "choices": {
                                        "Purple": "Purple",
                                        "Green": "Green"
                                    },
                                    "default_value": [
                                        "Purple"
                                    ],
                                    "allow_null": 0,
                                    "multiple": 0,
                                    "ui": 0,
                                    "ajax": 0,
                                    "return_format": "value",
                                    "placeholder": ""
                                },
                                {
                                    "key": "field_5c6f2341b98bb",
                                    "label": "Headline",
                                    "name": "headline",
                                    "type": "text",
                                    "instructions": "",
                                    "required": 0,
                                    "conditional_logic": 0,
                                    "wrapper": {
                                        "width": "",
                                        "class": "",
                                        "id": ""
                                    },
                                    "default_value": "",
                                    "placeholder": "",
                                    "prepend": "",
                                    "append": "",
                                    "maxlength": ""
                                },
                                {
                                    "key": "field_5c6f2341b98bc",
                                    "label": "Text",
                                    "name": "text",
                                    "type": "wysiwyg",
                                    "instructions": "",
                                    "required": 0,
                                    "conditional_logic": 0,
                                    "wrapper": {
                                        "width": "",
                                        "class": "",
                                        "id": ""
                                    },
                                    "default_value": "",
                                    "tabs": "all",
                                    "toolbar": "very_simple",
                                    "media_upload": 0,
                                    "delay": 0
                                },
                                {
                                    "key": "field_5c6f2341b98bd",
                                    "label": "Link",
                                    "name": "link",
                                    "type": "link",
                                    "instructions": "",
                                    "required": 0,
                                    "conditional_logic": 0,
                                    "wrapper": {
                                        "width": "",
                                        "class": "",
                                        "id": ""
                                    },
                                    "return_format": "array"
                                }
                            ]
                        }
                    ],
                    "min": "",
                    "max": ""
                },
                "layout_5c386cd4b557a": {
                    "key": "layout_5c386cd4b557a",
                    "name": "horizontal_button_block",
                    "label": "Horizontal Button Block",
                    "display": "block",
                    "sub_fields": [
                        {
                            "key": "field_5c6f2341b98be",
                            "label": "buttons",
                            "name": "buttons",
                            "type": "repeater",
                            "instructions": "",
                            "required": 0,
                            "conditional_logic": 0,
                            "wrapper": {
                                "width": "",
                                "class": "",
                                "id": ""
                            },
                            "collapsed": "field_5c386d14b557c",
                            "min": 1,
                            "max": 3,
                            "layout": "row",
                            "button_label": "",
                            "sub_fields": [
                                {
                                    "key": "field_5c6f2341b98bf",
                                    "label": "Link",
                                    "name": "link",
                                    "type": "link",
                                    "instructions": "",
                                    "required": 0,
                                    "conditional_logic": 0,
                                    "wrapper": {
                                        "width": "",
                                        "class": "",
                                        "id": ""
                                    },
                                    "return_format": "array"
                                }
                            ]
                        }
                    ],
                    "min": "",
                    "max": ""
                },
                "layout_5c42d086b8450": {
                    "key": "layout_5c42d086b8450",
                    "name": "infographic_block",
                    "label": "Infographic Block",
                    "display": "block",
                    "sub_fields": [
                        {
                            "key": "field_5c6f2341b98c0",
                            "label": "Content",
                            "name": "content",
                            "type": "post_object",
                            "instructions": "",
                            "required": 0,
                            "conditional_logic": 0,
                            "wrapper": {
                                "width": "",
                                "class": "",
                                "id": ""
                            },
                            "post_type": [
                                "infographics"
                            ],
                            "taxonomy": "",
                            "allow_null": 0,
                            "multiple": 0,
                            "return_format": "object",
                            "ui": 1
                        }
                    ],
                    "min": "",
                    "max": ""
                }
            },
            "button_label": "New Article Item",
            "min": "",
            "max": ""
        }
    ],
    "location": [
        [
            {
                "param": "post_type",
                "operator": "==",
                "value": "resourcelibrary"
            }
        ]
    ],
    "menu_order": 0,
    "position": "normal",
    "style": "default",
    "label_placement": "top",
    "instruction_placement": "label",
    "hide_on_screen": [
        "the_content",
        "excerpt",
        "discussion",
        "comments",
        "revisions",
        "slug",
        "author",
        "format",
        "page_attributes",
        "featured_image",
        "tags",
        "send-trackbacks"
    ],
    "active": true,
    "description": "",
    "modified": 1551950965
}